detection_tools/__init__.py
detection_tools/core/__init__.py
detection_tools/core/anchor_generator.py
detection_tools/core/balanced_positive_negative_sampler.py
detection_tools/core/balanced_positive_negative_sampler_test.py
detection_tools/core/batch_multiclass_nms_test.py
detection_tools/core/batcher.py
detection_tools/core/batcher_tf1_test.py
detection_tools/core/box_coder.py
detection_tools/core/box_coder_test.py
detection_tools/core/box_list.py
detection_tools/core/box_list_ops.py
detection_tools/core/box_list_ops_test.py
detection_tools/core/box_list_test.py
detection_tools/core/box_predictor.py
detection_tools/core/class_agnostic_nms_test.py
detection_tools/core/data_decoder.py
detection_tools/core/data_parser.py
detection_tools/core/densepose_ops.py
detection_tools/core/densepose_ops_test.py
detection_tools/core/freezable_batch_norm.py
detection_tools/core/freezable_batch_norm_tf2_test.py
detection_tools/core/freezable_sync_batch_norm.py
detection_tools/core/keypoint_ops.py
detection_tools/core/keypoint_ops_test.py
detection_tools/core/losses.py
detection_tools/core/losses_test.py
detection_tools/core/matcher.py
detection_tools/core/matcher_test.py
detection_tools/core/minibatch_sampler.py
detection_tools/core/minibatch_sampler_test.py
detection_tools/core/model.py
detection_tools/core/model_test.py
detection_tools/core/multiclass_nms_test.py
detection_tools/core/post_processing.py
detection_tools/core/prefetcher.py
detection_tools/core/prefetcher_tf1_test.py
detection_tools/core/preprocessor.py
detection_tools/core/preprocessor_cache.py
detection_tools/core/preprocessor_test.py
detection_tools/core/region_similarity_calculator.py
detection_tools/core/region_similarity_calculator_test.py
detection_tools/core/standard_fields.py
detection_tools/core/target_assigner.py
detection_tools/core/target_assigner_test.py
detection_tools/utils/__init__.py
detection_tools/utils/autoaugment_utils.py
detection_tools/utils/bifpn_utils.py
detection_tools-0.3.dist-info/LICENSE
detection_tools-0.3.dist-info/METADATA
detection_tools-0.3.dist-info/WHEEL
detection_tools-0.3.dist-info/top_level.txt
detection_tools-0.3.dist-info/RECORD
